pyasn1/__init__.py
pyasn1/debug.py
pyasn1/error.py
pyasn1/codec/__init__.py
pyasn1/codec/ber/__init__.py
pyasn1/codec/ber/decoder.py
pyasn1/codec/ber/encoder.py
pyasn1/codec/ber/eoo.py
pyasn1/codec/cer/__init__.py
pyasn1/codec/cer/decoder.py
pyasn1/codec/cer/encoder.py
pyasn1/codec/der/__init__.py
pyasn1/codec/der/decoder.py
pyasn1/codec/der/encoder.py
pyasn1/codec/native/__init__.py
pyasn1/codec/native/decoder.py
pyasn1/codec/native/encoder.py
pyasn1/compat/__init__.py
pyasn1/compat/binary.py
pyasn1/compat/calling.py
pyasn1/compat/dateandtime.py
pyasn1/compat/integer.py
pyasn1/compat/octets.py
pyasn1/compat/string.py
pyasn1/type/__init__.py
pyasn1/type/base.py
pyasn1/type/char.py
pyasn1/type/constraint.py
pyasn1/type/error.py
pyasn1/type/namedtype.py
pyasn1/type/namedval.py
pyasn1/type/opentype.py
pyasn1/type/tag.py
pyasn1/type/tagmap.py
pyasn1/type/univ.py
pyasn1/type/useful.py
pyasn1-0.4.7.dist-info/LICENSE.rst
pyasn1-0.4.7.dist-info/METADATA
pyasn1-0.4.7.dist-info/WHEEL
pyasn1-0.4.7.dist-info/top_level.txt
pyasn1-0.4.7.dist-info/zip-safe
pyasn1-0.4.7.dist-info/RECORD
